libreeye/__init__.py
libreeye/camera.py
libreeye/gc.py
libreeye/md.py
libreeye/recorder.py
libreeye/algorithms/__init__.py
libreeye/algorithms/motion.py
libreeye/daemon/__init__.py
libreeye/daemon/control.py
libreeye/daemon/daemon.py
libreeye/daemon/definitions.py
libreeye/daemon/socket_actions.py
libreeye/fs/__init__.py
libreeye/fs/aws.py
libreeye/fs/base.py
libreeye/fs/local.py
libreeye/package_data/etc/libreeye/aws_credentials
libreeye/package_data/etc/libreeye/cameras.conf
libreeye/package_data/etc/libreeye/libreeye.conf
libreeye/package_data/etc/libreeye/storage.conf
libreeye/package_data/etc/libreeye/cameras.d/sample.conf
libreeye/package_data/etc/systemd/libreeye.service
libreeye/sinks/__init__.py
libreeye/sinks/aws_bucket.py
libreeye/sinks/file.py
libreeye/sinks/interface.py
libreeye-0.4.1.dist-info/LICENSE.md
libreeye-0.4.1.dist-info/METADATA
libreeye-0.4.1.dist-info/WHEEL
libreeye-0.4.1.dist-info/entry_points.txt
libreeye-0.4.1.dist-info/top_level.txt
libreeye-0.4.1.dist-info/RECORD
